coco_api/__init__.py
coco_api/api.py
coco_api-0.0.2.dist-info/METADATA
coco_api-0.0.2.dist-info/WHEEL
coco_api-0.0.2.dist-info/top_level.txt
coco_api-0.0.2.dist-info/RECORD
