Metadata-Version: 2.4
Name: coco-api
Version: 0.0.2
Summary: A middleware rich backend framework for building APIs.
Author-email: A S Nandanunni <asnqln@gmail.com>
Requires-Python: >=3.8
